confiky/__init__.py
confiky-0.1.11.dist-info/METADATA
confiky-0.1.11.dist-info/RECORD
confiky-0.1.11.dist-info/WHEEL
confiky-0.1.11.dist-info/top_level.txt
