Metadata-Version: 2.1
Name: confiky
Version: 0.1.11
Summary: Read one or more .ini config file and return sections and params as object attributes
Home-page: https://github.com/acarmisc/confiky
Author: Andrea Carmisciano
Author-email: andrea.carmisciano@gmail.com
License: UNKNOWN
Platform: UNKNOWN
Requires-Dist: ConfigParser
